mseep_serena-0.1.3.dist-info/licenses/LICENSE
test/__init__.py
test/conftest.py
test/serena/__init__.py
test/serena/test_edit_marker.py
test/serena/test_make_tool_process_isolation.py
test/serena/test_mcp.py
test/serena/test_serena_agent.py
test/serena/test_symbol.py
test/serena/test_symbol_editing.py
test/serena/test_text_utils.py
mseep_serena-0.1.3.dist-info/METADATA
mseep_serena-0.1.3.dist-info/WHEEL
mseep_serena-0.1.3.dist-info/top_level.txt
mseep_serena-0.1.3.dist-info/RECORD
